sap_functions/__init__.py
sap_functions/base_sap_connection.py
sap_functions/grid.py
sap_functions/label.py
sap_functions/node.py
sap_functions/sap.py
sap_functions/session.py
sap_functions/table.py
sap_functions/tree.py
sap_functions/utils.py
sap_functions-1.3.dist-info/METADATA
sap_functions-1.3.dist-info/WHEEL
sap_functions-1.3.dist-info/licenses/LICENSE
sap_functions-1.3.dist-info/RECORD
