Metadata-Version: 2.4
Name: sap_functions
Version: 1.3
Summary: A utility package for sap automations
Project-URL: Homepage, https://github.com/RA4Z/sap_functions
Project-URL: Repository, https://github.com/RA4Z/sap_functions
Project-URL: Issues, https://github.com/RA4Z/sap_functions/issues
Author-email: Gabriel Volles Marinho <gabrielvmarinho1711@gmail.com>, Robert Aron Zimmermann <robert.raz@gmail.com>
License-Expression: MIT
License-File: LICENSE
Classifier: Operating System :: Microsoft :: Windows
Classifier: Programming Language :: Python :: 3
Requires-Python: >=3.9
Requires-Dist: pywin32==311
